setup.py
carrots/__init__.py
carrots/microconsumer.py
carrots/microproducer.py
carrots/microworker.py
carrots.egg-info/PKG-INFO
carrots.egg-info/SOURCES.txt
carrots.egg-info/dependency_links.txt
carrots.egg-info/not-zip-safe
carrots.egg-info/requires.txt
carrots.egg-info/top_level.txt
carrots/common/__init__.py
carrots/common/functions.py
carrots/common/microclient.py