Metadata-Version: 1.0
Name: carrots
Version: 0.1.12
Summary: Library to build RabbitMQ architectures like you were playing with lego blocks
Home-page: http://github.com/croccam/carrots
Author: Croccam
Author-email: antcarri@gmail.com
License: MIT
Platform: UNKNOWN
